{
  "title": "Casual shots with Leica T",
  "content": "Mostly shot with Leica T + TL 23mm.\nA few with Leica M9P + Rollei 40mm.\n",
  "summary": "Mostly shot with Leica T + TL 23mm.\nA few with Leica M9P + Rollei 40mm.\n",
  "date": "2025-08-23T00:19:31-04:00",
  "lastmod": "2025-08-23T00:19:31-04:00",
  "permalink": "https://nianze.github.io/zh/gallery/digital/2025/08/23/2025-08-23-weekly-visual-project/",
  "type": "gallery",
  "kind": "page",
  "section": "gallery",
  "tags": ["street photography"],
  "categories": ["visual"],
  "series": ["weekly"]
}
